aws_resource_scheduler/__init__.py
aws_resource_scheduler/scheduler.py
aws_resource_scheduler/utils/__init__.py
aws_resource_scheduler/utils/asg.py
aws_resource_scheduler/utils/aurora.py
aws_resource_scheduler/utils/common.py
aws_resource_scheduler/utils/ec2.py
aws_resource_scheduler/utils/ecs.py
aws_resource_scheduler/utils/rds.py
aws_resource_scheduler-0.1.0.dist-info/LICENSE
aws_resource_scheduler-0.1.0.dist-info/METADATA
aws_resource_scheduler-0.1.0.dist-info/WHEEL
aws_resource_scheduler-0.1.0.dist-info/entry_points.txt
aws_resource_scheduler-0.1.0.dist-info/top_level.txt
aws_resource_scheduler-0.1.0.dist-info/RECORD
