Metadata-Version: 2.1
Name: aws-resource-scheduler
Version: 0.1.0
Summary: An open-source solution to start/stop AWS EC2, Autoscaling Group, RDS, Aurora, ECS, and Fargate.
Author-email: Nitin Bhadauria <nitinb@cloudstaff.com>
Maintainer-email: Nitin Bhadauria <nitinb@cloudstaff.com>
License: MIT
Project-URL: Homepage, https://github.com/cloudstaff-apps/aws-resource-scheduler
Project-URL: Repository, https://github.com/cloudstaff-apps/aws-resource-scheduler
Project-URL: Documentation, https://github.com/cloudstaff-apps/aws-resource-scheduler#readme
Project-URL: BugTracker, https://github.com/cloudstaff-apps/aws-resource-scheduler/issues
Keywords: aws,scheduler,automation,ec2,rds,asg,aurora
Classifier: Programming Language :: Python :: 3
Classifier: License :: OSI Approved :: MIT License
Classifier: Operating System :: OS Independent
Requires-Python: >=3.8
License-File: LICENSE
Requires-Dist: boto3>=1.20.0
Requires-Dist: PyYAML>=5.4
Requires-Dist: requests>=2.28.2
